metric_visualizer/__init__.py
metric_visualizer/cli_command.py
metric_visualizer/colalab.py
metric_visualizer/metric_visualizer.py
metric_visualizer/utils.py
metric_visualizer/external/__init__.py
metric_visualizer/external/scott_knott.py
metric_visualizer-0.9.17.dist-info/LICENSE
metric_visualizer-0.9.17.dist-info/METADATA
metric_visualizer-0.9.17.dist-info/WHEEL
metric_visualizer-0.9.17.dist-info/entry_points.txt
metric_visualizer-0.9.17.dist-info/top_level.txt
metric_visualizer-0.9.17.dist-info/RECORD
