Metadata-Version: 2.1
Name: metric_visualizer
Version: 0.9.17
Summary: This is a tool for automated experimental metrics statistics and visualization
Home-page: https://github.com/yangheng95/metric_visualizer
Author: yang, Heng
Author-email: hy345@exeter.ac.uk
License: MIT
Requires-Python: >=3.6
License-File: LICENSE
Requires-Dist: matplotlib >=3.6.3
Requires-Dist: tikzplotlib
Requires-Dist: findfile
Requires-Dist: scipy
Requires-Dist: tabulate
Requires-Dist: natsort
Requires-Dist: numpy
Requires-Dist: update-checker
Requires-Dist: click
Requires-Dist: pandas
Requires-Dist: openpyxl
Requires-Dist: xlsxwriter
Requires-Dist: scikit-learn
Requires-Dist: colorama
